{
  "_metadata": {
    "description": "G.I. Joe Movies (2009-2021) — movie-original characters only. Returning characters (Duke, Snake Eyes, etc.) share ARAH slugs and get appearance records instead.",
    "total_characters": 5
  },
  "characters": [
    {
      "name": "Rex Lewis",
      "character_type": "Human",
      "alt_mode": null,
      "is_combined_form": false,
      "notes": "Movieverse ORIGINAL character. Movie-original Cobra Commander identity. Baroness's brother, former soldier turned mad scientist 'The Doctor'. Played by Joseph Gordon-Levitt in Rise of Cobra (2009). No ARAH equivalent — ARAH Cobra Commander has different origin",
      "slug": "rex-lewis",
      "faction_slug": "cobra",
      "sub_group_slugs": [],
      "continuity_family_slug": "gi-joe-movieverse",
      "franchise_slug": "gi-joe"
    },
    {
      "name": "Akiko",
      "character_type": "Human",
      "alt_mode": null,
      "is_combined_form": false,
      "notes": "Movieverse ORIGINAL character. Head of security for Arashikage clan. Played by Haruka Abe in Snake Eyes: G.I. Joe Origins (2021). No ARAH equivalent",
      "slug": "akiko",
      "faction_slug": "gi-joe",
      "sub_group_slugs": [],
      "continuity_family_slug": "gi-joe-movieverse",
      "franchise_slug": "gi-joe"
    },
    {
      "name": "Kenta",
      "character_type": "Human",
      "alt_mode": null,
      "is_combined_form": false,
      "notes": "Movieverse ORIGINAL character. Arashikage exile and yakuza leader. Played by Takehiro Hira in Snake Eyes: G.I. Joe Origins (2021). No ARAH equivalent",
      "slug": "kenta",
      "faction_slug": "cobra",
      "sub_group_slugs": [],
      "continuity_family_slug": "gi-joe-movieverse",
      "franchise_slug": "gi-joe"
    },
    {
      "name": "Sen",
      "character_type": "Human",
      "alt_mode": null,
      "is_combined_form": false,
      "notes": "Movieverse ORIGINAL character. Elder of the Arashikage clan. Played by Eri Ishida in Snake Eyes: G.I. Joe Origins (2021). No ARAH equivalent",
      "slug": "sen",
      "faction_slug": "gi-joe",
      "sub_group_slugs": [],
      "continuity_family_slug": "gi-joe-movieverse",
      "franchise_slug": "gi-joe"
    },
    {
      "name": "Mouse",
      "character_type": "Human",
      "alt_mode": null,
      "is_combined_form": false,
      "notes": "Movieverse ORIGINAL character. Young G.I. Joe tech specialist. Played by Joseph Mazzello in Retaliation (2013). No ARAH equivalent",
      "slug": "mouse",
      "faction_slug": "gi-joe",
      "sub_group_slugs": [],
      "continuity_family_slug": "gi-joe-movieverse",
      "franchise_slug": "gi-joe"
    }
  ]
}
